LICENSE.txt
MANIFEST.in
README.rst
pyproject.toml
setup.py
docs/__init__.py
docs/conf.py
requirements/base.in
requirements/dev.txt
requirements/plugins.txt
tests/test_bindmount.py
tests/test_config.py
tests/test_env.py
tests/test_plugin_indexes.py
tests/test_plugins.py
tests/test_plugins_v0.py
tests/test_serialize.py
tests/test_utils.py
tutor/__about__.py
tutor/__init__.py
tutor/bindmount.py
tutor/config.py
tutor/env.py
tutor/exceptions.py
tutor/fmt.py
tutor/images.py
tutor/interactive.py
tutor/py.typed
tutor/serialize.py
tutor/tasks.py
tutor/types.py
tutor/utils.py
tutor.egg-info/PKG-INFO
tutor.egg-info/SOURCES.txt
tutor.egg-info/dependency_links.txt
tutor.egg-info/entry_points.txt
tutor.egg-info/requires.txt
tutor.egg-info/top_level.txt
tutor/commands/__init__.py
tutor/commands/cli.py
tutor/commands/compose.py
tutor/commands/config.py
tutor/commands/context.py
tutor/commands/dev.py
tutor/commands/images.py
tutor/commands/jobs.py
tutor/commands/jobs_utils.py
tutor/commands/k8s.py
tutor/commands/local.py
tutor/commands/mounts.py
tutor/commands/params.py
tutor/commands/plugins.py
tutor/commands/upgrade/__init__.py
tutor/commands/upgrade/common.py
tutor/commands/upgrade/compose.py
tutor/commands/upgrade/k8s.py
tutor/core/__init__.py
tutor/core/hooks/__init__.py
tutor/core/hooks/actions.py
tutor/core/hooks/contexts.py
tutor/core/hooks/filters.py
tutor/core/hooks/priorities.py
tutor/hooks/__init__.py
tutor/hooks/catalog.py
tutor/plugins/__init__.py
tutor/plugins/base.py
tutor/plugins/indexes.py
tutor/plugins/openedx.py
tutor/plugins/v0.py
tutor/plugins/v1.py
tutor/templates/kustomization.yml
tutor/templates/version
tutor/templates/apps/caddy/Caddyfile
tutor/templates/apps/openedx/uwsgi.ini
tutor/templates/apps/openedx/config/cms.env.yml
tutor/templates/apps/openedx/config/lms.env.yml
tutor/templates/apps/openedx/config/partials/auth.yml
tutor/templates/apps/openedx/settings/cms/__init__.py
tutor/templates/apps/openedx/settings/cms/development.py
tutor/templates/apps/openedx/settings/cms/production.py
tutor/templates/apps/openedx/settings/cms/test.py
tutor/templates/apps/openedx/settings/lms/__init__.py
