Metadata-Version: 2.1
Name: tutor
Version: 19.0.1
Summary: The Docker-based Open edX distribution designed for peace of mind
Home-page: https://docs.tutor.edly.io/
Author: Edly
Author-email: hello@edly.io
License: AGPLv3
Project-URL: Documentation, https://docs.tutor.edly.io/
Project-URL: Code, https://github.com/overhangio/tutor
Project-URL: Issue tracker, https://github.com/overhangio/tutor/issues
Project-URL: Community, https://discuss.openedx.org/tag/tutor
Platform: UNKNOWN
Classifier: Development Status :: 5 - Production/Stable
Classifier: Intended Audience :: Developers
Classifier: License :: OSI Approved :: GNU Affero General Public License v3
Classifier: Operating System :: OS Independent
Classifier: Programming Language :: Python
Classifier: Programming Language :: Python :: 3.9
Classifier: Programming Language :: Python :: 3.10
Classifier: Programming Language :: Python :: 3.11
Classifier: Programming Language :: Python :: 3.12
Requires-Python: >=3.9
Provides-Extra: dev
Provides-Extra: full
License-File: LICENSE.txt
